recsim_ng/__init__.py
recsim_ng/applications/__init__.py
recsim_ng/applications/demo.py
recsim_ng/applications/ecosystem_simulation/__init__.py
recsim_ng/applications/ecosystem_simulation/corpus.py
recsim_ng/applications/ecosystem_simulation/corpus_test.py
recsim_ng/applications/ecosystem_simulation/ecosystem_simulation.py
recsim_ng/applications/ecosystem_simulation/ecosystem_simulation_demo.py
recsim_ng/applications/ecosystem_simulation/ecosystem_simulation_test.py
recsim_ng/applications/ecosystem_simulation/metrics.py
recsim_ng/applications/ecosystem_simulation/metrics_test.py
recsim_ng/applications/ecosystem_simulation/recommender.py
recsim_ng/applications/ecosystem_simulation/recommender_test.py
recsim_ng/applications/ecosystem_simulation/simulation_config.py
recsim_ng/applications/ecosystem_simulation/user.py
recsim_ng/applications/ecosystem_simulation/user_test.py
recsim_ng/applications/latent_variable_model_learning/__init__.py
recsim_ng/applications/latent_variable_model_learning/latent_variable_model_demo.py
recsim_ng/applications/latent_variable_model_learning/latent_variable_model_test.py
recsim_ng/applications/latent_variable_model_learning/recommender.py
recsim_ng/applications/latent_variable_model_learning/recommender_test.py
recsim_ng/applications/latent_variable_model_learning/simulation_config.py
recsim_ng/applications/latent_variable_model_learning/user.py
recsim_ng/applications/latent_variable_model_learning/user_test.py
recsim_ng/applications/recsys_partially_observable_rl/__init__.py
recsim_ng/applications/recsys_partially_observable_rl/corpus.py
recsim_ng/applications/recsys_partially_observable_rl/corpus_test.py
recsim_ng/applications/recsys_partially_observable_rl/interest_evolution_simulation.py
recsim_ng/applications/recsys_partially_observable_rl/interest_evolution_simulation_demo.py
recsim_ng/applications/recsys_partially_observable_rl/interest_evolution_simulation_test.py
recsim_ng/applications/recsys_partially_observable_rl/metrics.py
recsim_ng-0.1.1.dist-info/LICENSE
recsim_ng-0.1.1.dist-info/METADATA
recsim_ng-0.1.1.dist-info/WHEEL
recsim_ng-0.1.1.dist-info/top_level.txt
recsim_ng-0.1.1.dist-info/RECORD
