Metadata-Version: 2.1
Name: recsim-ng
Version: 0.1.1
Summary: RecSim NG: Toward Principled Uncertainty Modeling for Recommender Ecosystems
Home-page: https://github.com/google-research/recsim_ng
Author: The RecSim Team
Author-email: no-reply@google.com
License: Apache 2.0
Project-URL: Documentation, https://github.com/google-research/recsim_ng
Project-URL: Bug Reports, https://github.com/google-research/recsim_ng/issues
Project-URL: Source, https://github.com/google-research/recsim_ng
Keywords: recsim reinforcement-learning recommender-system simulation probabilistic-programming
Platform: UNKNOWN
Classifier: Development Status :: 3 - Alpha
Classifier: Intended Audience :: Developers
Classifier: Intended Audience :: Education
Classifier: Intended Audience :: Science/Research
Classifier: License :: OSI Approved :: Apache Software License
Classifier: Programming Language :: Python
Classifier: Programming Language :: Python :: 3.6
Classifier: Topic :: Scientific/Engineering
Classifier: Topic :: Scientific/Engineering :: Mathematics
Classifier: Topic :: Scientific/Engineering :: Artificial Intelligence
Classifier: Topic :: Software Development
Classifier: Topic :: Software Development :: Libraries
Classifier: Topic :: Software Development :: Libraries :: Python Modules
Requires-Python: >=3.6
Requires-Dist: absl-py
Requires-Dist: edward2
Requires-Dist: gin-config
Requires-Dist: gym
Requires-Dist: matplotlib
Requires-Dist: numpy
Requires-Dist: tensorflow (>=2.3.0)
Requires-Dist: tensorflow-probability
